alacritty_colorscheme/__init__.py
alacritty_colorscheme/cli.py
alacritty_colorscheme/colorscheme.py
alacritty_colorscheme/vim.py
alacritty_colorscheme-1.0.1.dist-info/entry_points.txt
alacritty_colorscheme-1.0.1.dist-info/WHEEL
alacritty_colorscheme-1.0.1.dist-info/METADATA
alacritty_colorscheme-1.0.1.dist-info/RECORD
