Metadata-Version: 2.1
Name: alacritty-colorscheme
Version: 1.0.1
Summary: Change colorscheme of alacritty with ease
Home-page: https://github.com/toggle-corp/alacritty-colorscheme/
License: Apache-2.0
Keywords: alacritty,colorscheme,theme,base16,vim
Author: Safar Ligal
Author-email: weathermist@gmail.com
Requires-Python: >=3.6,<4.0
Classifier: Environment :: Console
Classifier: Intended Audience :: Developers
Classifier: License :: OSI Approved :: Apache Software License
Classifier: Natural Language :: English
Classifier: Programming Language :: Python :: 3
Classifier: Programming Language :: Python :: 3.6
Classifier: Programming Language :: Python :: 3.7
Classifier: Programming Language :: Python :: 3.8
Classifier: Programming Language :: Python :: 3.9
Requires-Dist: pynvim (>=0.4.2,<0.5.0)
Requires-Dist: ruamel.yaml (>=0.16.10,<0.17.0)
Requires-Dist: typed-argument-parser (>=1.6.3,<2.0.0)
Requires-Dist: typing-extensions (>=3.10.0,<4.0.0)
Project-URL: Repository, https://github.com/toggle-corp/alacritty-colorscheme/
